HtmlElementAttributes/__init__.py
HtmlElementAttributes/html_element_attributes.py
html_element_attributes-0.1.2.dist-info/LICENSE
html_element_attributes-0.1.2.dist-info/WHEEL
html_element_attributes-0.1.2.dist-info/METADATA
html_element_attributes-0.1.2.dist-info/RECORD
