Metadata-Version: 2.1
Name: html-element-attributes
Version: 0.1.2
Summary: List of known HTML tag attributes
Home-page: https://github.com/Riverside-Healthcare/html-element-attributes
License: GPL-3.0-or-later
Author: Christopher Pickering
Author-email: cpickering@rhc.net
Requires-Python: >=3.7,<4.0
Classifier: License :: OSI Approved :: GNU General Public License v3 or later (GPLv3+)
Classifier: Programming Language :: Python :: 3
Classifier: Programming Language :: Python :: 3.10
Classifier: Programming Language :: Python :: 3.7
Classifier: Programming Language :: Python :: 3.8
Classifier: Programming Language :: Python :: 3.9
Project-URL: Repository, https://github.com/Riverside-Healthcare/html-element-attributes
